rcsb/__init__.py
rcsb/utils/__init__.py
rcsb/utils/citation/CitationReferenceProvider.py
rcsb/utils/citation/JournalTitleAbbreviationProvider.py
rcsb/utils/citation/PubMedReader.py
rcsb/utils/citation/PubMedUtils.py
rcsb/utils/citation/__init__.py
rcsb.utils.citation-0.24.dist-info/LICENSE
rcsb.utils.citation-0.24.dist-info/METADATA
rcsb.utils.citation-0.24.dist-info/WHEEL
rcsb.utils.citation-0.24.dist-info/top_level.txt
rcsb.utils.citation-0.24.dist-info/RECORD
