Metadata-Version: 2.1
Name: rcsb.utils.citation
Version: 0.24
Summary: RCSB Python utility classes to manage PDB citation data
Home-page: https://github.com/rcsb/py-rcsb_utils_citation
Author: John Westbrook
Author-email: john.westbrook@rcsb.org
License: Apache 2.0
Classifier: Development Status :: 3 - Alpha
Classifier: Intended Audience :: Developers
Classifier: Natural Language :: English
Classifier: License :: OSI Approved :: Apache Software License
Classifier: Programming Language :: Python
Classifier: Programming Language :: Python :: 3
Classifier: Programming Language :: Python :: 3.10
License-File: LICENSE
Requires-Dist: rcsb.utils.io>=1.15
Requires-Dist: nltk>=3.2.5
Requires-Dist: regex<2022.3.2,>=2019.11.1
Provides-Extra: dev
Requires-Dist: check-manifest; extra == "dev"
Provides-Extra: test
Requires-Dist: coverage; extra == "test"
